AUTHORS.rst
CONTRIBUTING.rst
HISTORY.rst
LICENSE
MANIFEST.in
README.rst
setup.cfg
setup.py
BioID/BioID.py
BioID/__init__.py
BioID.egg-info/PKG-INFO
BioID.egg-info/SOURCES.txt
BioID.egg-info/dependency_links.txt
BioID.egg-info/requires.txt
BioID.egg-info/top_level.txt
BioID.egg-info/zip-safe
docs/Makefile
docs/authors.rst
docs/conf.py
docs/contributing.rst
docs/history.rst
docs/index.rst
docs/installation.rst
docs/make.bat
docs/readme.rst
docs/usage.rst
tests/.DS_Store
tests/__init__.py
tests/format_tests.csv
tests/test_BioID.py
tests/testFiles/AAA03323.embl
tests/testFiles/DD231055_edited.embl
tests/testFiles/Human_contigs.embl
tests/testFiles/NC_000932.fa
tests/testFiles/NC_000932.gb
tests/testFiles/TRBG361.embl
tests/testFiles/apaf.xml
tests/testFiles/bats.nex
tests/testFiles/bcl_2.xml
tests/testFiles/blank_seq.gb
tests/testFiles/characters.xml
tests/testFiles/codonposset.nex
tests/testFiles/cw02.aln
tests/testFiles/distribution.xml
tests/testFiles/dna_example.xml
tests/testFiles/error_diff_ids.fq
tests/testFiles/error_qual_space.fq
tests/testFiles/ex1_refresh.bam
tests/testFiles/example.xml
tests/testFiles/extra_keywords.gb
tests/testFiles/f001
tests/testFiles/f002
tests/testFiles/f003
tests/testFiles/fa01
tests/testFiles/fp_no_header.phy
tests/testFiles/fp_no_seq.phy
tests/testFiles/funny.sth
tests/testFiles/global_species_example.xml
tests/testFiles/greek.sff
tests/testFiles/hedgehog.aln
tests/testFiles/hennigian.phy
tests/testFiles/horses.phy
tests/testFiles/int_node_labels.nwk
tests/testFiles/interleaved.phy
tests/testFiles/longreads_as_sanger.fq
tests/testFiles/made_up.xml
tests/testFiles/o_tol_332_d_dollo.xml
tests/testFiles/odd_consensus.aln
tests/testFiles/opuntia.aln
tests/testFiles/paired.sff
tests/testFiles/phenoscape.xml
tests/testFiles/phyloxml_examples.xml
tests/testFiles/protein_example.xml
tests/testFiles/rna_example.xml
tests/testFiles/sequential.phy
tests/testFiles/simple.sth
tests/testFiles/simple_ascii.txt
tests/testFiles/solexa_full_range_as_illumina.fq
tests/testFiles/testFiles.txt
tests/testFiles/trees.xml
tests/testFiles/tricky.fq